AsiaChannel/__init__.py
AsiaChannel/audio/__init__.py
AsiaChannel/video/__init__.py
test/__init__.py
AsiaChannel-2023.9.1.dist-info/LICENSE.txt
AsiaChannel-2023.9.1.dist-info/METADATA
AsiaChannel-2023.9.1.dist-info/WHEEL
AsiaChannel-2023.9.1.dist-info/top_level.txt
AsiaChannel-2023.9.1.dist-info/RECORD
